<?xml version="1.0" encoding="UTF-8"?><loader name="EBS_FA" refreshPeriod="900" schema="EBS_FA" version="1.0" xml:base="schemas/513_loader.xml"><datasets><sql source="Vision" table="EBS_FA.FA_BOOKS"><query>select * from fa_books</query></sql><sql source="Vision" table="EBS_FA.FA_BOOK_CONTROLS"><query>select * from fa_book_controls</query></sql><sql source="Vision" table="EBS_FA.fa_balances_reports_itf"><query>select * from fa_balances_reports_itf</query></sql><sql source="Vision" table="EBS_FA.fa_distribution_history"><query>select * from fa_distribution_history</query></sql><sql source="Vision" table="EBS_FA.fa_transaction_headers"><query>select * from fa_transaction_headers</query></sql><sql source="Vision" table="EBS_FA.fa_asset_history"><query>select * from fa_asset_history</query></sql><sql source="Vision" table="EBS_FA.fa_mc_adjustments"><query>select * from fa_mc_adjustments</query></sql><sql source="Vision" table="EBS_FA.fa_deprn_periods"><query>select * from fa_deprn_periods</query></sql><sql source="Vision" table="EBS_FA.fa_mc_books"><query>select * from fa_mc_books</query></sql><sql source="Vision" table="EBS_FA.fa_mc_deprn_detail"><query>select * from fa_mc_deprn_detail</query></sql><sql source="Vision" table="EBS_FA.fa_deprn_detail"><query>select * from fa_deprn_detail</query></sql><sql source="Vision" table="EBS_FA.fa_group_asset_default"><query>select * from fa_group_asset_default</query></sql><sql source="Vision" table="EBS_FA.fa_category_books"><query>select * from fa_category_books</query></sql><sql source="Vision" table="EBS_FA.fa_books_groups_mrc_v"><query>select * from fa_books_groups_mrc_v</query></sql><sql source="Vision" table="EBS_FA.fa_mc_deprn_summary"><query>select * from fa_mc_deprn_summary</query></sql><sql source="Vision" table="EBS_FA.fa_group_asset_rules"><query>select * from fa_group_asset_rules</query></sql><sql source="Vision" table="EBS_FA.fa_deprn_summary"><query>select * from fa_deprn_summary</query></sql><sql source="Vision" table="EBS_FA.fa_worker_jobs"><query>select * from fa_worker_jobs</query></sql><sql source="Vision" table="EBS_FA.fa_adjustments"><query>select * from fa_adjustments</query></sql><sql source="Vision" table="EBS_FA.fa_additions_b"><query>select * from fa_additions_b</query></sql><sql source="Vision" table="EBS_FA.fa_mc_deprn_periods"><query>select * from fa_mc_deprn_periods</query></sql><sql source="Vision" table="EBS_FA.fa_categories_b"><query>select * from fa_categories_b</query></sql><sql source="Vision" table="EBS_FA.fa_retirements"><query>select * from fa_retirements</query></sql></datasets></loader>