<?xml version="1.0" encoding="UTF-8"?><schema description="" loader="STANFORD" name="STANFORD" version="0.1"><tables><table alias="false" name="Billing" source="Stanford"><column encrypt="false" function="dimension" hide="false" label="Seq Id" name="SEQ_ID" type="integer"/><column encrypt="false" function="dimension" hide="false" label="Profile Class Name" name="PROFILE_CLASS_NAME" type="string"/><column encrypt="false" function="measure" hide="false" label="Surcharge Rate" name="SURCHARGE_RATE" type="double"/><column encrypt="false" function="dimension" hide="false" label="Student Charge" name="STUDENT_CHARGE" type="string"/><column encrypt="false" function="dimension" hide="false" label="Student Credit" name="STUDENT_CREDIT" type="string"/><column encrypt="false" function="dimension" hide="false" label="Asset Intance Id" name="ASSET_INTANCE_ID" type="integer"/><column encrypt="false" function="dimension" hide="false" label="Asset Group" name="ASSET_GROUP" type="string"/><column encrypt="false" function="dimension" hide="false" label="Acct Budget Unit" name="ACCT_BUDGET_UNIT" type="string"/><column encrypt="false" function="dimension" hide="false" label="Acct Account Title" name="ACCT_ACCOUNT_TITLE" type="string"/><column encrypt="false" function="dimension" hide="false" label="Acct Rptg Project" name="ACCT_RPTG_PROJECT" type="string"/><column encrypt="false" function="dimension" hide="false" label="Acct Rptg Task" name="ACCT_RPTG_TASK" type="string"/><column encrypt="false" function="dimension" hide="false" label="Acct Rptg Award" name="ACCT_RPTG_AWARD" type="string"/><column encrypt="false" function="dimension" hide="false" label="Acct Rptg Exp Type" name="ACCT_RPTG_EXP_TYPE" type="string"/><column encrypt="false" function="dimension" hide="false" label="Acct Reptg Exp Org" name="ACCT_REPTG_EXP_ORG" type="string"/><column encrypt="false" function="dimension" hide="false" label="Acct Occ Cost Ctr" name="ACCT_OCC_COST_CTR" type="string"/><column encrypt="false" function="dimension" hide="false" label="Acct Mrc Cost Ctr" name="ACCT_MRC_COST_CTR" type="string"/><column encrypt="false" function="dimension" hide="false" label="Acct Occ Cost Ctr Name" name="ACCT_OCC_COST_CTR_NAME" type="string"/><column encrypt="false" function="dimension" hide="false" label="Acct Mrc Cost Ctr Name" name="ACCT_MRC_COST_CTR_NAME" type="string"/><column encrypt="false" function="dimension" hide="false" label="Work Order Type" name="WORK_ORDER_TYPE" type="string"/><column encrypt="false" function="dimension" hide="false" label="Work Order Number" name="WORK_ORDER_NUMBER" type="string"/><column encrypt="false" function="dimension" hide="false" label="Pmg Order Number" name="PMG_ORDER_NUMBER" type="string"/><column encrypt="false" function="dimension" hide="false" label="Wo Activity Cause" name="WO_ACTIVITY_CAUSE" type="string"/><column encrypt="false" function="dimension" hide="false" label="Wo Asset Activity" name="WO_ASSET_ACTIVITY" type="string"/><column encrypt="false" function="dimension" hide="false" label="Wo Owning Dept" name="WO_OWNING_DEPT" type="string"/><column encrypt="false" function="dimension" hide="false" label="Work Order Status" name="WORK_ORDER_STATUS" type="string"/><column encrypt="false" function="dimension" hide="false" label="Requested Completion Date" name="REQUESTED_COMPLETION_DATE" type="date"/><column encrypt="false" function="dimension" hide="false" label="Requested End Service Date" name="REQUESTED_END_SERVICE_DATE" type="date"/><column encrypt="false" function="dimension" hide="false" label="Wo Activity Type" name="WO_ACTIVITY_TYPE" type="string"/><column encrypt="false" function="dimension" hide="false" label="Wip Entity Id" name="WIP_ENTITY_ID" type="integer"/><column encrypt="false" function="dimension" hide="false" label="Pta Project" name="PTA_PROJECT" type="string"/><column encrypt="false" function="dimension" hide="false" label="Pta Task" name="PTA_TASK" type="string"/><column encrypt="false" function="dimension" hide="false" label="Pta Award" name="PTA_AWARD" type="string"/><column encrypt="false" function="dimension" hide="false" label="Pta Task Owning Org" name="PTA_TASK_OWNING_ORG" type="string"/><column encrypt="false" function="dimension" hide="false" label="Pta Task Budget Unit" name="PTA_TASK_BUDGET_UNIT" type="string"/><column encrypt="false" function="dimension" hide="false" label="Pta Expenditure Type" name="PTA_EXPENDITURE_TYPE" type="string"/><column encrypt="false" function="dimension" hide="false" label="Pfoo Project" name="PFOO_PROJECT" type="string"/><column encrypt="false" function="dimension" hide="false" label="Pfoo Fund" name="PFOO_FUND" type="string"/><column encrypt="false" function="dimension" hide="false" label="Pfoo Org" name="PFOO_ORG" type="string"/><column encrypt="false" function="dimension" hide="false" label="Pfoo Dist Id" name="PFOO_DIST_ID" type="integer"/><column encrypt="false" function="dimension" hide="false" label="Operation Seq Number" name="OPERATION_SEQ_NUMBER" type="integer"/><column encrypt="false" function="dimension" hide="false" label="Operation Description" name="OPERATION_DESCRIPTION" type="string"/><column encrypt="false" function="dimension" hide="false" label="Inventory Item Number" name="INVENTORY_ITEM_NUMBER" type="string"/><column encrypt="false" function="dimension" hide="false" label="Item Revenue Plan" name="ITEM_REVENUE_PLAN" type="string"/><column encrypt="false" function="dimension" hide="false" label="Item Bill Recurrence" name="ITEM_BILL_RECURRENCE" type="string"/><column encrypt="false" function="dimension" hide="false" label="Item Markup" name="ITEM_MARKUP" type="string"/><column encrypt="false" function="dimension" hide="false" label="Inventory Item Id" name="INVENTORY_ITEM_ID" type="integer"/><column encrypt="false" function="dimension" hide="false" label="Mtl Bill Start Date" name="MTL_BILL_START_DATE" type="date"/><column encrypt="false" function="dimension" hide="false" label="Mtl Last Bill Date" name="MTL_LAST_BILL_DATE" type="date"/><column encrypt="false" function="measure" hide="false" label="Mtl Billed Quantity" name="MTL_BILLED_QUANTITY" type="integer"/><column encrypt="false" function="dimension" hide="false" label="Mtl Transaction Id" name="MTL_TRANSACTION_ID" type="integer"/><column encrypt="false" function="dimension" hide="false" label="Last Success Bill Date" name="LAST_SUCCESS_BILL_DATE" type="date"/><column encrypt="false" function="dimension" hide="false" label="Source File Name" name="SOURCE_FILE_NAME" type="string"/><column encrypt="false" function="dimension" hide="false" label="Price List Name" name="PRICE_LIST_NAME" type="string"/><column encrypt="false" function="measure" hide="false" label="Item Price" name="ITEM_PRICE" type="double"/><column encrypt="false" function="measure" hide="false" label="Num Of Days Billed" name="NUM_OF_DAYS_BILLED" type="double"/><column encrypt="false" function="measure" hide="false" label="Line Amount" name="LINE_AMOUNT" type="double"/><column encrypt="false" function="measure" hide="false" label="Surcharge Amount" name="SURCHARGE_AMOUNT" type="double"/><column encrypt="false" function="dimension" hide="false" label="Je Journal Id" name="JE_JOURNAL_ID" type="integer"/><column encrypt="false" function="dimension" hide="false" label="Pta Journal Line Id" name="PTA_JOURNAL_LINE_ID" type="integer"/><column encrypt="false" function="dimension" hide="false" label="Pfoo Journal Line Id" name="PFOO_JOURNAL_LINE_ID" type="integer"/><column encrypt="false" function="dimension" hide="false" label="Billing Batch Id" name="BILLING_BATCH_ID" type="integer"/><column encrypt="false" function="dimension" hide="false" label="Invoice Header Id" name="INVOICE_HEADER_ID" type="integer"/><column encrypt="false" function="dimension" hide="false" label="Distribution Line Id" name="DISTRIBUTION_LINE_ID" type="integer"/><column encrypt="false" function="dimension" hide="false" label="Billing Source" name="BILLING_SOURCE" type="string"/><column encrypt="false" function="dimension" hide="false" label="Gl Period" name="GL_PERIOD" type="string"/><column encrypt="false" function="dimension" hide="false" label="Expense Period" name="EXPENSE_PERIOD" type="string"/><column encrypt="false" function="dimension" hide="false" label="Ps Term Code" name="PS_TERM_CODE" type="string"/><column encrypt="false" function="measure" hide="false" label="Created By" name="CREATED_BY" type="integer"/><column encrypt="false" function="measure" hide="false" label="Last Updated By" name="LAST_UPDATED_BY" type="integer"/><column encrypt="false" function="dimension" hide="false" label="Creation Date" name="CREATION_DATE" type="date"/><column encrypt="false" function="dimension" hide="false" label="Last Update Date" name="LAST_UPDATE_DATE" type="date"/><column encrypt="false" function="dimension" hide="false" label="Request Id" name="REQUEST_ID" type="integer"/><column encrypt="false" function="dimension" hide="false" label="Item Revenue Plan Desc" name="ITEM_REVENUE_PLAN_DESC" type="string"/><column encrypt="false" function="dimension" hide="false" label="Pn Loc Code 1" name="PN_LOC_CODE_1" type="string"/><column encrypt="false" function="dimension" hide="false" label="Telcom Room 1" name="TELCOM_ROOM_1" type="string"/><column encrypt="false" function="dimension" hide="false" label="Tso 1" name="TSO_1" type="string"/><column encrypt="false" function="dimension" hide="false" label="Pn Loc Code 2" name="PN_LOC_CODE_2" type="string"/><column encrypt="false" function="dimension" hide="false" label="Telcom Room 2" name="TELCOM_ROOM_2" type="string"/><column encrypt="false" function="dimension" hide="false" label="Tso 2" name="TSO_2" type="string"/><column encrypt="false" function="dimension" hide="false" label="Req Room 1" name="REQ_ROOM_1" type="string"/><column encrypt="false" function="dimension" hide="false" label="Req Room 2" name="REQ_ROOM_2" type="string"/><column encrypt="false" function="dimension" hide="false" label="Acct Period Id" name="ACCT_PERIOD_ID" type="integer"/><column encrypt="false" function="dimension" hide="false" label="Include Flag" name="INCLUDE_FLAG" type="string"/><column encrypt="false" function="dimension" hide="false" label="Fiscal Year" name="FISCAL_YEAR" type="integer"/><column encrypt="false" function="dimension" hide="false" label="Pfoo Object" name="PFOO_OBJECT" type="string"/><column encrypt="false" function="dimension" hide="false" label="Item Revenue Plan Srv Cat" name="ITEM_REVENUE_PLAN_SRV_CAT" type="string"/><column encrypt="false" function="dimension" hide="false" label="Item Revenue Plan Funding" name="ITEM_REVENUE_PLAN_FUNDING" type="string"/><column encrypt="false" function="dimension" hide="false" label="Last Login Qb" name="LAST_LOGIN_QB" type="string"/><column encrypt="false" function="dimension" hide="false" label="Last Login Building Name" name="LAST_LOGIN_BUILDING_NAME" type="string"/><column encrypt="false" function="dimension" hide="false" label="Last Login Building Address" name="LAST_LOGIN_BUILDING_ADDRESS" type="string"/><column encrypt="false" function="dimension" hide="false" label="Pta Exp Type Desc" name="PTA_EXP_TYPE_DESC" type="string"/><column encrypt="false" function="dimension" hide="false" label="Item Description" name="ITEM_DESCRIPTION" type="string"/><column encrypt="false" function="dimension" hide="false" label="Organization Id" name="ORGANIZATION_ID" type="integer"/></table><table alias="false" name="Periods" source="periods.csv"><column encrypt="false" function="dimension" hide="false" label="Period" name="Period" type="string"/><column encrypt="false" function="dimension" hide="false" label="Order" name="Order" type="integer"/></table><table alias="false" name="FiscalPeriod" source="FiscalPeriod.csv"><column encrypt="false" function="dimension" hide="false" label="Period Number" name="PeriodNumber" type="integer"/><column encrypt="false" function="dimension" hide="false" label="Period" name="Period" type="string"/><column encrypt="false" function="dimension" hide="false" label="Fiscal Quarter" name="FiscalQuarter" type="string"/><column encrypt="false" function="dimension" hide="false" label="Fiscal Year" name="FiscalYear" type="integer"/><column encrypt="false" function="dimension" hide="false" label="Period Start Date" name="PeriodStartDate" type="date"/></table><table alias="false" name="EAM_Tables" source="EAM_Tables.xlsx"><column function="dimension" hide="false" label="Runtime" name="RUNTIME" type="string"/><column function="dimension" hide="false" label="Actiontype" name="ActionType" type="string"/><column function="dimension" hide="false" label="Schema" name="Schema" type="string"/><column function="dimension" hide="false" label="Table" name="Table" type="string"/><column function="measure" hide="false" label="Duration" name="Duration" type="double"/><column function="dimension" hide="false" label="Unknown" name="unknown" type="string"/><column function="measure" hide="false" label="Numberofrows" name="NumberOfRows" type="integer"/></table></tables><joins><join name="b05c2464-00a3-3a08-088f-61cfc79faea3"><cond child="STANFORD.Billing.GL_PERIOD" op="=" parent="STANFORD.Periods.Period"/></join><join name="fc2df2b5-b4ca-9c1c-bf87-573739fbd902"><cond child="STANFORD.Billing.GL_PERIOD" op="=" parent="STANFORD.FiscalPeriod.Period"/></join></joins></schema>