<?xml version="1.0" encoding="UTF-8"?><report name="Eric" version="" schema=""><defaultTables> <defaultTable schema="Avago" table="Lookup"/> <defaultTable schema="Avago" table="OnHand"/> <defaultTable schema="Avago" table="SafetyStock"/> <defaultTable schema="EBS_CUST" table="GL_DATE"/></defaultTables><layout><table id="585f9cf8-1f51-0318-b31e-1d6433814fc3" maxRows="0" autoRefresh="true" oldTable="true" aggregation="true" total="false" subtotal="false"><properties><property name="caption" value=""/><property name="numberOfElementsInRow" value="2"/><property name="height" value="450"/><property name="automaticHeight" value="0"/></properties><binding><row field="Avago.OnHand.Avago_Part_No" label="Avago Part No" datatype= "string"  function= "dimension"  hierarchy= "false" ><format type="0"></format></row><measure field="Avago.OnHand.On_Hand_Qty__SUM_" label="On Hand Qty  Sum " aggregation="sum" runningTotal="false" function= "measure" ><format seriesType = "line" ></format><properties><property name="format" value="###,###.00"/></properties></measure></binding><format coloringScheme="0" showLegend="1"/></table><table id="f4d72f8d-0c87-f068-8f5e-357a51d616a7" maxRows="0" autoRefresh="true" oldTable="true" aggregation="true" total="false" subtotal="false"><properties><property name="caption" value=""/><property name="numberOfElementsInRow" value="2"/><property name="height" value="450"/><property name="automaticHeight" value="0"/></properties><binding><row field="Avago.OnHand.Avago_Part_No" label="Avago Part No" datatype= "string"  function= "dimension"  hierarchy= "false" ><format type="0"></format></row><measure field="Avago.OnHand.DATE_RECEIVED" label="Date Received" aggregation="count" runningTotal="false" function= "dimension" ><format numberFormat = "6" seriesType = "line" ></format><properties><property name="format" value="#.##"/></properties></measure></binding><format coloringScheme="0" showLegend="1"/></table><table id="2ba6960b-6811-3fec-6950-4c703d017dff" maxRows="0" autoRefresh="true" oldTable="true" aggregation="true" total="false" subtotal="false"><properties><property name="caption" value=""/><property name="numberOfElementsInRow" value="1"/><property name="height" value="450"/><property name="automaticHeight" value="0"/></properties><binding></binding><format coloringScheme="0" showLegend="1"/></table><table id="f2162bb4-175a-3d8c-e746-17138a804983" maxRows="0" autoRefresh="true" oldTable="true" aggregation="true" total="false" subtotal="false"><properties><property name="caption" value=""/><property name="numberOfElementsInRow" value="1"/><property name="height" value="450"/><property name="automaticHeight" value="0"/></properties><binding><measure field="opsmaster.ops.PN_" label="Pn " aggregation="count" runningTotal="false" function= "dimension" ><format numberFormat = "6" seriesType = "line" ></format><properties><property name="format" value="#.##"/></properties></measure><measure field="opsmaster.ops.Commit_Code" label="Commit Code" aggregation="count" runningTotal="false" function= "dimension" ><format numberFormat = "6" seriesType = "line" ></format><properties><property name="format" value="#.##"/></properties></measure><measure field="opsmaster.ops.Supplier" label="Supplier" aggregation="count" runningTotal="false" function= "measure" ><format seriesType = "line" ></format><properties><property name="format" value="###,###.00"/></properties></measure></binding><format coloringScheme="0" showLegend="1"/></table></layout></report>