<?xml version="1.0" encoding="UTF-8"?><report name="Klaus5" schema="" version="" xml:base="dashboards/392_dashboard.xml"><prompts> <dimPrompt default="false" field="SALES.Countries.COUNTRY_ID" function="measure" label="Country Id" type="multiple"/></prompts><defaultTables> <defaultTable schema="SALES" table="Countries"/></defaultTables><layout><table aggregation="false" id="ed8a096b-f33f-49f4-006b-9a64b2e6bcbb" maxRows="0" subtotal="false" total="false"><properties><property name="caption" value=""/><property name="numberOfElementsInRow" value="1"/><property name="height" value="450"/><property name="automaticHeight" value="0"/></properties><binding><measure aggregation="sum" field="SALES.Countries.COUNTRY_ID" function="measure" label="Country Id" runningTotal="false"><format numberFormat="6" seriesType="line"/><properties><property name="format" value="#.##"/></properties></measure><measure aggregation="count" field="SALES.Countries.COUNTRY_NAME" function="dimension" label="Country Name" runningTotal="false"><format numberFormat="6" seriesType="line"/><properties><property name="format" value="#.##"/></properties></measure></binding><format coloringScheme="0" showLegend="1"/></table></layout></report>