{
"type":"layout",
"comp": [
{
"id":"8a4c17f4-7f89-3cbc-610d-3721e1a3160a",
"type":"table",
"isSampled":false,
"isAggregated":true,
"endRow":1000,
"mergeColumns":false,
"labels":["Name","# of Cases"],
"rowTypes":["string"],
"measureTypes":["double"],
"totalRows":2,
"complete":true,
"rowTree":{
"g":[{
"v":"John",
"rowNo":0,
"rs":1,
"t":[{
"v":"1"}]},
{
"v":"Steve",
"rowNo":0,
"rs":1,
"t":[{
"v":"3"}]}]}},
{
"id":"cf72531d-405e-2ef9-7d7e-bfe734d39e1c",
"type":"table",
"isSampled":false,
"isAggregated":true,
"endRow":1000,
"mergeColumns":false,
"labels":["Open Date","Name","Status","Name","Case Number"],
"rowTypes":["date","string","string","string"],
"measureTypes":["double"],
"totalRows":4,
"complete":true,
"rowTree":{
"g":[{
"v":"2/1/16",
"rv":"2016-02-01 00:00:00",
"rowNo":0,
"rs":1,
"g":[{
"v":"Walmart",
"rowNo":1,
"rs":1,
"g":[{
"v":"close",
"rowNo":2,
"rs":1,
"g":[{
"v":"John",
"rowNo":3,
"rs":1,
"t":[{
"v":"1"}]}]}]}]},
{
"v":"3/25/16",
"rv":"2016-03-25 00:00:00",
"rowNo":0,
"rs":1,
"g":[{
"v":"Walmart",
"rowNo":1,
"rs":1,
"g":[{
"v":"close",
"rowNo":2,
"rs":1,
"g":[{
"v":"Steve",
"rowNo":3,
"rs":1,
"t":[{
"v":"3"}]}]}]}]},
{
"v":"6/28/16",
"rv":"2016-06-28 00:00:00",
"rowNo":0,
"rs":1,
"g":[{
"v":"Walmart",
"rowNo":1,
"rs":1,
"g":[{
"v":"open",
"rowNo":2,
"rs":1,
"g":[{
"v":"Steve",
"rowNo":3,
"rs":1,
"t":[{
"v":"8"}]}]}]}]},
{
"v":"6/30/16",
"rv":"2016-06-30 00:00:00",
"rowNo":0,
"rs":1,
"g":[{
"v":"Walmart",
"rowNo":1,
"rs":1,
"g":[{
"v":"open",
"rowNo":2,
"rs":1,
"g":[{
"v":"Steve",
"rowNo":3,
"rs":1,
"t":[{
"v":"11"}]}]}]}]}]}},
{
"id":"aea1096f-2ea2-e753-94b9-373e90625654",
"type":"chart",
"graph_type":"column",
"isSampled":false,
"row":"A_01_CASE.date_open.Month_Name",
"xAxisCount":1,
"yAxisCount":1,
"axisLabels":["Month Name","Case Number"],
"dataTypeXAxis":"string",
"labels":["Month Name","Case Number"],
"average":[null],
"cells":[["February",1.0],
["March",1.0],
["June",2.0]],
"result":0}]
}
